journeylib/__init__.py
journeylib/funciones.py
journeylib/lib_test.py
journeylib/tests.py
journeylib-2.0.12.dist-info/METADATA
journeylib-2.0.12.dist-info/WHEEL
journeylib-2.0.12.dist-info/top_level.txt
journeylib-2.0.12.dist-info/RECORD
