Metadata-Version: 2.1
Name: journeylib
Version: 2.0.12
Summary: Libreria para gestionar datos del historico del proyecto GPTravel
Home-page: https://ismigit.fi.upm.es/gptravel-2024/ai-squad/journeygenai
Author: Equipo JourneyGen UPM
Author-email: f.gonzalez.lopez@alumnos.upm.es
License: MIT
Platform: UNKNOWN
